README.md
setup.py
kookaburra.egg-info/PKG-INFO
kookaburra.egg-info/SOURCES.txt
kookaburra.egg-info/dependency_links.txt
kookaburra.egg-info/entry_points.txt
kookaburra.egg-info/requires.txt
kookaburra.egg-info/top_level.txt
src/.version
src/__init__.py
src/data.py
src/database.py
src/flux.py
src/likelihood.py
src/plot.py
src/priors.py
src/single_pulse.py