Metadata-Version: 1.2
Name: kookaburra
Version: 0.2.0
Summary: Shapelet fitting for pulsars
Home-page: https://github.com/GregoryAshton/kookaburra
Author: Greg Ashton
Author-email: gregory.ashton@ligo.org
License: MIT
Platform: UNKNOWN
Classifier: Programming Language :: Python :: 3.7
Classifier: License :: OSI Approved :: MIT License
Classifier: Operating System :: OS Independent
Requires-Python: >3.6
